LICENSE.md
README.md
setup.py
lsuv/__init__.py
lsuv/lsuvinit.py
lsuv.egg-info/PKG-INFO
lsuv.egg-info/SOURCES.txt
lsuv.egg-info/dependency_links.txt
lsuv.egg-info/not-zip-safe
lsuv.egg-info/top_level.txt
test/test_lsuv.py